texutils_hw2/__init__.py
texutils_hw2/image.py
texutils_hw2/table.py
texutils_hw2-1.1.dist-info/METADATA
texutils_hw2-1.1.dist-info/WHEEL
texutils_hw2-1.1.dist-info/top_level.txt
texutils_hw2-1.1.dist-info/RECORD
